LICENSE
README.md
setup.py
stochdepth/__init__.py
stochdepth/func.py
stochdepth/hook.py
stochdepth/iterator.py
stochdepth/target.py
stochdepth/uniform.py
stochdepth.egg-info/PKG-INFO
stochdepth.egg-info/SOURCES.txt
stochdepth.egg-info/dependency_links.txt
stochdepth.egg-info/requires.txt
stochdepth.egg-info/top_level.txt