Metadata-Version: 2.1
Name: stochdepth
Version: 0.5.0
Summary: A simple hook based implementation of "Deep Networks with Stochastic Depth" for torchvision resnets.
Home-page: https://github.com/tasptz/pytorch-stochastic-depth
Author: Thomas Pönitz
Author-email: tasptz@gmail.com
License: MIT
Platform: any
License-File: LICENSE
